Workbook

Sheet Raw_Data
A1: Transaction ID | B1: Customer ID | C1: Category | D1: Item | E1: Price Per Unit | F1: Quantity | G1: Total Spent | H1: Payment Method | I1: Location | J1: Transaction Date | K1: Discount Applied
A2: TXN_6867343 | B2: CUST_09 | C2: Patisserie | D2: Item_10_PAT | E2: 18.5 | F2: 10 | G2: 185 | H2: Digital Wallet | I2: Online | J2: 45390 | K2: TRUE
A3: TXN_3731986 | B3: CUST_22 | C3: Milk Products | D3: Item_17_MILK | E3: 29 | F3: 9 | G3: 261 | H3: Digital Wallet | I3: Online | J3: 45130 | K3: TRUE
A4: TXN_9303719 | B4: CUST_02 | C4: Butchers | D4: Item_12_BUT | E4: 21.5 | F4: 2 | G4: 43 | H4: Credit Card | I4: Online | J4: 44839 | K4: FALSE
A5: TXN_9458126 | B5: CUST_06 | C5: Beverages | D5: Item_16_BEV | E5: 27.5 | F5: 9 | G5: 247.5 | H5: Credit Card | I5: Online | J5: 44688
A6: TXN_4575373 | B6: CUST_05 | C6: Food | D6: Item_6_FOOD | E6: 12.5 | F6: 7 | G6: 87.5 | H6: Digital Wallet | I6: Online | J6: 44836 | K6: FALSE
A7: TXN_7482416 | B7: CUST_09 | C7: Patisserie | F7: 10 | G7: 200 | H7: Credit Card | I7: Online | J7: 45260
A8: TXN_3652209 | B8: CUST_07 | C8: Food | D8: Item_1_FOOD | E8: 5 | F8: 8 | G8: 40 | H8: Credit Card | I8: In-store | J8: 45087 | K8: TRUE
A9: TXN_1372952 | B9: CUST_21 | C9: Furniture | E9: 33.5 | H9: Digital Wallet | I9: In-store | J9: 45384 | K9: TRUE
A10: TXN_9728486 | B10: CUST_23 | C10: Furniture | D10: Item_16_FUR | E10: 27.5 | F10: 1 | G10: 27.5 | H10: Credit Card | I10: In-store | J10: 45042 | K10: FALSE
A11: TXN_2722661 | B11: CUST_25 | C11: Butchers | D11: Item_22_BUT | E11: 36.5 | F11: 3 | G11: 109.5 | H11: Cash | I11: Online | J11: 45365 | K11: FALSE
A12: TXN_8776416 | B12: CUST_22 | C12: Butchers | D12: Item_3_BUT | E12: 8 | F12: 9 | G12: 72 | H12: Cash | I12: In-store | J12: 45640 | K12: TRUE
A13: TXN_5422631 | B13: CUST_09 | C13: Milk Products | F13: 8 | G13: 52 | H13: Digital Wallet | I13: In-store | J13: 45669 | K13: TRUE
A14: TXN_5874772 | B14: CUST_23 | C14: Food | D14: Item_2_FOOD | E14: 6.5 | F14: 7 | G14: 45.5 | H14: Cash | I14: Online | J14: 45178 | K14: TRUE
A15: TXN_4413070 | B15: CUST_14 | C15: Patisserie | D15: Item_24_PAT | E15: 39.5 | F15: 6 | G15: 237 | H15: Digital Wallet | I15: In-store | J15: 44701 | K15: FALSE
A16: TXN_2490363 | B16: CUST_09 | C16: Milk Products | D16: Item_16_MILK | E16: 27.5 | F16: 2 | G16: 55 | H16: Digital Wallet | I16: Online | J16: 44703
A17: TXN_1809665 | B17: CUST_14 | C17: Beverages | E17: 24.5 | H17: Credit Card | I17: In-store | J17: 44692
A18: TXN_7563311 | B18: CUST_23 | C18: Patisserie | D18: Item_17_PAT | E18: 29 | F18: 8 | G18: 232 | H18: Cash | I18: Online | J18: 45612 | K18: TRUE
A19: TXN_9634894 | B19: CUST_15 | C19: Milk Products | F19: 10 | G19: 275 | H19: Digital Wallet | I19: Online | J19: 44668
A20: TXN_4396807 | B20: CUST_17 | C20: Electric household essentials | D20: Item_13_EHE | E20: 23 | F20: 1 | G20: 23 | H20: Digital Wallet | I20: In-store | J20: 44599 | K20: FALSE
A21: TXN_4206593 | B21: CUST_01 | C21: Furniture | E21: 35 | H21: Digital Wallet | I21: Online | J21: 45670 | K21: FALSE
A22: TXN_9939063 | B22: CUST_14 | C22: Beverages | D22: Item_7_BEV | E22: 14 | F22: 9 | G22: 126 | H22: Digital Wallet | I22: In-store | J22: 45305
A23: TXN_8685338 | B23: CUST_15 | C23: Milk Products | F23: 3 | G23: 105 | H23: Credit Card | I23: In-store | J23: 45228
A24: TXN_6547964 | B24: CUST_10 | C24: Electric household essentials | D24: Item_4_EHE | E24: 9.5 | F24: 7 | G24: 66.5 | H24: Cash | I24: In-store | J24: 44788
A25: TXN_3314099 | B25: CUST_04 | C25: Food | D25: Item_10_FOOD | E25: 18.5 | F25: 1 | G25: 18.5 | H25: Cash | I25: Online | J25: 45199 | K25: FALSE
A26: TXN_9980736 | B26: CUST_13 | C26: Furniture | D26: Item_14_FUR | E26: 24.5 | F26: 2 | G26: 49 | H26: Cash | I26: Online | J26: 45167 | K26: FALSE
A27: TXN_3481599 | B27: CUST_05 | C27: Furniture | E27: 39.5 | H27: Cash | I27: Online | J27: 44812 | K27: FALSE
A28: TXN_9057609 | B28: CUST_18 | C28: Butchers | D28: Item_20_BUT | E28: 33.5 | F28: 4 | G28: 134 | H28: Credit Card | I28: In-store | J28: 44636 | K28: TRUE
A29: TXN_1599706 | B29: CUST_14 | C29: Furniture | D29: Item_25_FUR | E29: 41 | F29: 10 | G29: 410 | H29: Credit Card | I29: In-store | J29: 45375 | K29: TRUE
A30: TXN_1598860 | B30: CUST_08 | C30: Food | D30: Item_14_FOOD | E30: 24.5 | F30: 10 | G30: 245 | H30: Cash | I30: In-store | J30: 44857 | K30: TRUE
A31: TXN_7138501 | B31: CUST_18 | C31: Patisserie | D31: Item_22_PAT | E31: 36.5 | F31: 5 | G31: 182.5 | H31: Credit Card | I31: In-store | J31: 44630 | K31: FALSE
A32: TXN_5444504 | B32: CUST_05 | C32: Food | D32: Item_11_FOOD | E32: 20 | F32: 10 | G32: 200 | H32: Digital Wallet | I32: Online | J32: 44677 | K32: FALSE
A33: TXN_4353295 | B33: CUST_22 | C33: Patisserie | D33: Item_6_PAT | E33: 12.5 | F33: 8 | G33: 100 | H33: Credit Card | I33: Online | J33: 44656 | K33: TRUE
A34: TXN_1543244 | B34: CUST_20 | C34: Food | F34: 8 | G34: 196 | H34: Credit Card | I34: Online | J34: 45590 | K34: TRUE
A35: TXN_1494700 | B35: CUST_12 | C35: Electric household essentials | D35: Item_21_EHE | E35: 35 | F35: 9 | G35: 315 | H35: Credit Card | I35: In-store | J35: 45358
A36: TXN_1621497 | B36: CUST_06 | C36: Patisserie | E36: 23 | H36: Cash | I36: In-store | J36: 44975
A37: TXN_6398436 | B37: CUST_15 | C37: Beverages | D37: Item_25_BEV | E37: 41 | F37: 7 | G37: 287 | H37: Credit Card | I37: In-store | J37: 45446 | K37: TRUE
A38: TXN_9065245 | B38: CUST_02 | C38: Food | D38: Item_23_FOOD | E38: 38 | F38: 2 | G38: 76 | H38: Digital Wallet | I38: In-store | J38: 45361 | K38: FALSE
A39: TXN_6963438 | B39: CUST_11 | C39: Furniture | D39: Item_10_FUR | E39: 18.5 | F39: 5 | G39: 92.5 | H39: Credit Card | I39: Online | J39: 45405 | K39: TRUE
A40: TXN_8312797 | B40: CUST_14 | C40: Beverages | D40: Item_11_BEV | E40: 20 | F40: 5 | G40: 100 | H40: Digital Wallet | I40: Online | J40: 44715
A41: TXN_5836005 | B41: CUST_19 | C41: Butchers | D41: Item_23_BUT | E41: 38 | F41: 5 | G41: 190 | H41: Credit Card | I41: In-store | J41: 45584 | K41: FALSE
A42: TXN_4223250 | B42: CUST_16 | C42: Beverages | D42: Item_22_BEV | E42: 36.5 | F42: 7 | G42: 255.5 | H42: Cash | I42: Online | J42: 45077 | K42: TRUE
A43: TXN_1019817 | B43: CUST_16 | C43: Electric household essentials | D43: Item_10_EHE | E43: 18.5 | F43: 5 | G43: 92.5 | H43: Cash | I43: Online | J43: 44774
A44: TXN_1110407 | B44: CUST_25 | C44: Butchers | D44: Item_24_BUT | E44: 39.5 | F44: 7 | G44: 276.5 | H44: Digital Wallet | I44: In-store | J44: 44855
A45: TXN_6276518 | B45: CUST_24 | C45: Beverages | D45: Item_8_BEV | E45: 15.5 | F45: 3 | G45: 46.5 | H45: Cash | I45: In-store | J45: 45390
A46: TXN_4740738 | B46: CUST_25 | C46: Food | D46: Item_3_FOOD | E46: 8 | F46: 1 | G46: 8 | H46: Digital Wallet | I46: In-store | J46: 44670
A47: TXN_9587232 | B47: CUST_20 | C47: Food | D47: Item_12_FOOD | E47: 21.5 | F47: 5 | G47: 107.5 | H47: Digital Wallet | I47: Online | J47: 44985 | K47: TRUE
A48: TXN_6404316 | B48: CUST_04 | C48: Computers and electric accessories | D48: Item_16_CEA | E48: 27.5 | F48: 6 | G48: 165 | H48: Credit Card | I48: Online | J48: 44657 | K48: FALSE
A49: TXN_9331642 | B49: CUST_12 | C49: Patisserie | D49: Item_11_PAT | E49: 20 | F49: 4 | G49: 80 | H49: Credit Card | I49: Online | J49: 44748 | K49: TRUE
A50: TXN_9729422 | B50: CUST_13 | C50: Butchers | D50: Item_16_BUT | E50: 27.5 | F50: 6 | G50: 165 | H50: Credit Card | I50: Online | J50: 45657 | K50: TRUE
A51: TXN_8425168 | B51: CUST_25 | C51: Milk Products | D51: Item_16_MILK | E51: 27.5 | F51: 7 | G51: 192.5 | H51: Cash | I51: In-store | J51: 44632
A52: TXN_5379241 | B52: CUST_05 | C52: Butchers | D52: Item_20_BUT | E52: 33.5 | F52: 10 | G52: 335 | H52: Credit Card | I52: In-store | J52: 45028 | K52: FALSE
A53: TXN_8413369 | B53: CUST_23 | C53: Computers and electric accessories | D53: Item_5_CEA | E53: 11 | F53: 6 | G53: 66 | H53: Credit Card | I53: Online | J53: 45360 | K53: TRUE
A54: TXN_4836321 | B54: CUST_21 | C54: Food | D54: Item_12_FOOD | E54: 21.5 | F54: 10 | G54: 215 | H54: Digital Wallet | I54: In-store | J54: 44940 | K54: FALSE
A55: TXN_9451794 | B55: CUST_24 | C55: Milk Products | D55: Item_19_MILK | E55: 32 | F55: 3 | G55: 96 | H55: Credit Card | I55: Online | J55: 45319
A56: TXN_8218431 | B56: CUST_01 | C56: Furniture | D56: Item_23_FUR | E56: 38 | F56: 5 | G56: 190 | H56: Digital Wallet | I56: Online | J56: 45045 | K56: FALSE
A57: TXN_2383377 | B57: CUST_15 | C57: Furniture | D57: Item_7_FUR | E57: 14 | F57: 3 | G57: 42 | H57: Digital Wallet | I57: In-store | J57: 45018
A58: TXN_7909783 | B58: CUST_12 | C58: Computers and electric accessories | D58: Item_5_CEA | E58: 11 | F58: 1 | G58: 11 | H58: Credit Card | I58: Online | J58: 45277 | K58: TRUE
A59: TXN_5046007 | B59: CUST_07 | C59: Computers and electric accessories | D59: Item_15_CEA | E59: 26 | F59: 9 | G59: 234 | H59: Cash | I59: Online | J59: 45495 | K59: TRUE
A60: TXN_6966182 | B60: CUST_02 | C60: Furniture | D60: Item_16_FUR | E60: 27.5 | F60: 9 | G60: 247.5 | H60: Cash | I60: Online | J60: 45541
A61: TXN_3424571 | B61: CUST_09 | C61: Milk Products | D61: Item_6_MILK | E61: 12.5 | F61: 7 | G61: 87.5 | H61: Credit Card | I61: Online | J61: 44939 | K61: FALSE
A62: TXN_6820452 | B62: CUST_10 | C62: Computers and electric accessories | D62: Item_24_CEA | E62: 39.5 | F62: 8 | G62: 316 | H62: Credit Card | I62: In-store | J62: 45034 | K62: FALSE
A63: TXN_1998771 | B63: CUST_25 | C63: Milk Products | D63: Item_16_MILK | E63: 27.5 | F63: 3 | G63: 82.5 | H63: Digital Wallet | I63: Online | J63: 45603 | K63: TRUE
A64: TXN_1132097 | B64: CUST_24 | C64: Patisserie | D64: Item_11_PAT | E64: 20 | F64: 9 | G64: 180 | H64: Credit Card | I64: In-store | J64: 45064 | K64: TRUE
A65: TXN_5418871 | B65: CUST_04 | C65: Computers and electric accessories | D65: Item_22_CEA | E65: 36.5 | F65: 7 | G65: 255.5 | H65: Cash | I65: In-store | J65: 44636 | K65: FALSE
A66: TXN_6952276 | B66: CUST_01 | C66: Food | D66: Item_22_FOOD | E66: 36.5 | F66: 10 | G66: 365 | H66: Credit Card | I66: Online | J66: 45506 | K66: TRUE
A67: TXN_6340470 | B67: CUST_17 | C67: Butchers | D67: Item_2_BUT | E67: 6.5 | F67: 6 | G67: 39 | H67: Credit Card | I67: In-store | J67: 44846
A68: TXN_5885894 | B68: CUST_01 | C68: Patisserie | D68: Item_14_PAT | E68: 24.5 | F68: 10 | G68: 245 | H68: Credit Card | I68: In-store | J68: 44601 | K68: FALSE
A69: TXN_3671271 | B69: CUST_18 | C69: Patisserie | D69: Item_12_PAT | E69: 21.5 | F69: 8 | G69: 172 | H69: Cash | I69: In-store | J69: 45257 | K69: FALSE
A70: TXN_2719047 | B70: CUST_03 | C70: Butchers | D70: Item_20_BUT | E70: 33.5 | F70: 4 | G70: 134 | H70: Credit Card | I70: Online | J70: 45251
A71: TXN_9908330 | B71: CUST_19 | C71: Food | D71: Item_18_FOOD | E71: 30.5 | F71: 4 | G71: 122 | H71: Credit Card | I71: Online | J71: 44833 | K71: TRUE
A72: TXN_2016332 | B72: CUST_17 | C72: Patisserie | D72: Item_1_PAT | E72: 5 | F72: 6 | G72: 30 | H72: Digital Wallet | I72: Online | J72: 44912 | K72: TRUE
A73: TXN_7363165 | B73: CUST_25 | C73: Beverages | D73: Item_4_BEV | E73: 9.5 | F73: 7 | G73: 66.5 | H73: Digital Wallet | I73: In-store | J73: 45010
A74: TXN_1260450 | B74: CUST_25 | C74: Furniture | D74: Item_22_FUR | E74: 36.5 | F74: 10 | G74: 365 | H74: Digital Wallet | I74: In-store | J74: 45284 | K74: TRUE
A75: TXN_6315447 | B75: CUST_21 | C75: Patisserie | D75: Item_7_PAT | E75: 14 | F75: 9 | G75: 126 | H75: Digital Wallet | I75: In-store | J75: 45669 | K75: FALSE
A76: TXN_5973228 | B76: CUST_12 | C76: Beverages | D76: Item_7_BEV | E76: 14 | F76: 6 | G76: 84 | H76: Digital Wallet | I76: Online | J76: 45285 | K76: TRUE
A77: TXN_2780662 | B77: CUST_02 | C77: Milk Products | D77: Item_19_MILK | E77: 32 | F77: 10 | G77: 320 | H77: Digital Wallet | I77: In-store | J77: 44945
A78: TXN_1142481 | B78: CUST_02 | C78: Beverages | D78: Item_22_BEV | E78: 36.5 | F78: 6 | G78: 219 | H78: Cash | I78: In-store | J78: 44964 | K78: TRUE
A79: TXN_3933685 | B79: CUST_09 | C79: Computers and electric accessories | D79: Item_20_CEA | E79: 33.5 | F79: 10 | G79: 335 | H79: Credit Card | I79: Online | J79: 44666
A80: TXN_8955685 | B80: CUST_24 | C80: Food | D80: Item_20_FOOD | E80: 33.5 | F80: 2 | G80: 67 | H80: Digital Wallet | I80: Online | J80: 45040
A81: TXN_1061030 | B81: CUST_20 | C81: Computers and electric accessories | D81: Item_22_CEA | E81: 36.5 | F81: 4 | G81: 146 | H81: Digital Wallet | I81: Online | J81: 45487 | K81: TRUE
A82: TXN_7821493 | B82: CUST_07 | C82: Patisserie | D82: Item_17_PAT | E82: 29 | F82: 10 | G82: 290 | H82: Credit Card | I82: In-store | J82: 45643
A83: TXN_8114453 | B83: CUST_10 | C83: Electric household essentials | D83: Item_21_EHE | E83: 35 | F83: 2 | G83: 70 | H83: Digital Wallet | I83: In-store | J83: 45055 | K83: FALSE
A84: TXN_8024803 | B84: CUST_09 | C84: Furniture | D84: Item_11_FUR | E84: 20 | F84: 8 | G84: 160 | H84: Digital Wallet | I84: In-store | J84: 45526 | K84: FALSE
A85: TXN_4532214 | B85: CUST_25 | C85: Patisserie | E85: 15.5 | H85: Credit Card | I85: In-store | J85: 45376 | K85: FALSE
A86: TXN_5062634 | B86: CUST_04 | C86: Patisserie | D86: Item_25_PAT | E86: 41 | F86: 2 | G86: 82 | H86: Credit Card | I86: Online | J86: 45113 | K86: TRUE
A87: TXN_8244728 | B87: CUST_08 | C87: Food | D87: Item_7_FOOD | E87: 14 | F87: 1 | G87: 14 | H87: Credit Card | I87: In-store | J87: 45409
A88: TXN_3858145 | B88: CUST_17 | C88: Furniture | D88: Item_21_FUR | E88: 35 | F88: 3 | G88: 105 | H88: Digital Wallet | I88: Online | J88: 45017
A89: TXN_2646301 | B89: CUST_18 | C89: Furniture | D89: Item_24_FUR | E89: 39.5 | F89: 9 | G89: 355.5 | H89: Credit Card | I89: In-store | J89: 44902 | K89: FALSE
A90: TXN_2414530 | B90: CUST_24 | C90: Milk Products | D90: Item_8_MILK | E90: 15.5 | F90: 8 | G90: 124 | H90: Cash | I90: Online | J90: 45463
A91: TXN_8322008 | B91: CUST_22 | C91: Food | D91: Item_4_FOOD | E91: 9.5 | F91: 3 | G91: 28.5 | H91: Cash | I91: In-store | J91: 45524 | K91: FALSE
A92: TXN_3035546 | B92: CUST_19 | C92: Beverages | D92: Item_14_BEV | E92: 24.5 | F92: 2 | G92: 49 | H92: Credit Card | I92: In-store | J92: 45119 | K92: TRUE
A93: TXN_7296720 | B93: CUST_18 | C93: Patisserie | D93: Item_4_PAT | E93: 9.5 | F93: 5 | G93: 47.5 | H93: Cash | I93: Online | J93: 45547
A94: TXN_8414071 | B94: CUST_20 | C94: Patisserie | D94: Item_12_PAT | E94: 21.5 | F94: 9 | G94: 193.5 | H94: Cash | I94: In-store | J94: 45048 | K94: TRUE
A95: TXN_5705131 | B95: CUST_19 | C95: Milk Products | D95: Item_4_MILK | E95: 9.5 | F95: 4 | G95: 38 | H95: Digital Wallet | I95: Online | J95: 45378 | K95: TRUE
A96: TXN_5938028 | B96: CUST_18 | C96: Computers and electric accessories | D96: Item_7_CEA | E96: 14 | F96: 1 | G96: 14 | H96: Digital Wallet | I96: Online | J96: 44977 | K96: TRUE
A97: TXN_1958345 | B97: CUST_08 | C97: Electric household essentials | D97: Item_4_EHE | E97: 9.5 | F97: 8 | G97: 76 | H97: Cash | I97: In-store | J97: 45471
A98: TXN_1528585 | B98: CUST_15 | C98: Electric household essentials | D98: Item_6_EHE | E98: 12.5 | F98: 1 | G98: 12.5 | H98: Credit Card | I98: In-store | J98: 45552
A99: TXN_9619859 | B99: CUST_01 | C99: Butchers | D99: Item_21_BUT | E99: 35 | F99: 4 | G99: 140 | H99: Cash | I99: In-store | J99: 45387 | K99: FALSE
A100: TXN_6158929 | B100: CUST_21 | C100: Food | D100: Item_11_FOOD | E100: 20 | F100: 6 | G100: 120 | H100: Cash | I100: Online | J100: 44590 | K100: TRUE
...

Sheet Cleaned_Data
A1: Transaction ID | B1: Customer ID | C1: Category | D1: Item | E1: Price Per Unit | F1: Quantity | G1: Total Spent | H1: Payment Method | I1: Location | J1: Transaction Date | K1: Discount Applied | L1: Total_Spent_validation | N1: 1 | O1: Item_Imputed | P1: Price_Imputed
A2: TXN_6867343 | B2: CUST_09 | C2: Patisserie | D2: Item_10_PAT | E2: 18.5 | F2: 10 | G2: 185 | H2: Digital Wallet | I2: Online | J2: 45390 | K2: TRUE | L2: =IF(OR(F2="",G2=""),"skip",IF(ROUND(E2*F2,2)=ROUND(G2,2),"OK","MISMATCH")) -> OK | N2: 2 | O2: NO | P2: NO
A3: TXN_3731986 | B3: CUST_22 | C3: Milk Products | D3: Item_17_MILK | E3: 29 | F3: 9 | G3: 261 | H3: Digital Wallet | I3: Online | J3: 45130 | K3: TRUE | L3: =IF(OR(F3="",G3=""),"skip",IF(ROUND(E3*F3,2)=ROUND(G3,2),"OK","MISMATCH")) -> OK | N3: 3 | O3: NO | P3: NO
A4: TXN_9303719 | B4: CUST_02 | C4: Butchers | D4: Item_12_BUT | E4: 21.5 | F4: 2 | G4: 43 | H4: Credit Card | I4: Online | J4: 44839 | K4: FALSE | L4: =IF(OR(F4="",G4=""),"skip",IF(ROUND(E4*F4,2)=ROUND(G4,2),"OK","MISMATCH")) -> OK | N4: 4 | O4: NO | P4: NO
A5: TXN_9458126 | B5: CUST_06 | C5: Beverages | D5: Item_16_BEV | E5: 27.5 | F5: 9 | G5: 247.5 | H5: Credit Card | I5: Online | J5: 44688 | L5: =IF(OR(F5="",G5=""),"skip",IF(ROUND(E5*F5,2)=ROUND(G5,2),"OK","MISMATCH")) -> OK | N5: 5 | O5: NO | P5: NO
A6: TXN_4575373 | B6: CUST_05 | C6: Food | D6: Item_6_FOOD | E6: 12.5 | F6: 7 | G6: 87.5 | H6: Digital Wallet | I6: Online | J6: 44836 | K6: FALSE | L6: =IF(OR(F6="",G6=""),"skip",IF(ROUND(E6*F6,2)=ROUND(G6,2),"OK","MISMATCH")) -> OK | N6: 6 | O6: NO | P6: NO
A7: TXN_7482416 | B7: CUST_09 | C7: Patisserie | D7: =_xlfn.XLOOKUP(E7,Lookup_PPU!W:W,Lookup_PPU!V:V,"NOT FOUND") -> Item_11_PAT | E7: =G7/F7 -> 20 | F7: 10 | G7: 200 | H7: Credit Card | I7: Online | J7: 45260 | L7: =IF(OR(F7="",G7=""),"skip",IF(ROUND(E7*F7,2)=ROUND(G7,2),"OK","MISMATCH")) -> OK | N7: 7 | O7: YES | P7: YES
A8: TXN_3652209 | B8: CUST_07 | C8: Food | D8: Item_1_FOOD | E8: 5 | F8: 8 | G8: 40 | H8: Credit Card | I8: In-store | J8: 45087 | K8: TRUE | L8: =IF(OR(F8="",G8=""),"skip",IF(ROUND(E8*F8,2)=ROUND(G8,2),"OK","MISMATCH")) -> OK | N8: 8 | O8: NO | P8: NO
A9: TXN_1372952 | B9: CUST_21 | C9: Furniture | D9: =_xlfn.XLOOKUP(E9,Lookup_PPU!Q:Q,Lookup_PPU!P:P, "NOT FOUND") -> Item_20_FUR | E9: 33.5 | H9: Digital Wallet | I9: In-store | J9: 45384 | K9: TRUE | L9: =IF(OR(F9="",G9=""),"skip",IF(ROUND(E9*F9,2)=ROUND(G9,2),"OK","MISMATCH")) -> skip | N9: 9 | O9: YES | P9: NO
A10: TXN_9728486 | B10: CUST_23 | C10: Furniture | D10: Item_16_FUR | E10: 27.5 | F10: 1 | G10: 27.5 | H10: Credit Card | I10: In-store | J10: 45042 | K10: FALSE | L10: =IF(OR(F10="",G10=""),"skip",IF(ROUND(E10*F10,2)=ROUND(G10,2),"OK","MISMATCH")) -> OK | N10: 10 | O10: NO | P10: NO
A11: TXN_2722661 | B11: CUST_25 | C11: Butchers | D11: Item_22_BUT | E11: 36.5 | F11: 3 | G11: 109.5 | H11: Cash | I11: Online | J11: 45365 | K11: FALSE | L11: =IF(OR(F11="",G11=""),"skip",IF(ROUND(E11*F11,2)=ROUND(G11,2),"OK","MISMATCH")) -> OK | N11: 11 | O11: NO | P11: NO
A12: TXN_8776416 | B12: CUST_22 | C12: Butchers | D12: Item_3_BUT | E12: 8 | F12: 9 | G12: 72 | H12: Cash | I12: In-store | J12: 45640 | K12: TRUE | L12: =IF(OR(F12="",G12=""),"skip",IF(ROUND(E12*F12,2)=ROUND(G12,2),"OK","MISMATCH")) -> OK | N12: 12 | O12: NO | P12: NO
A13: TXN_5422631 | B13: CUST_09 | C13: Milk Products | D13: =_xlfn.XLOOKUP(E13,Lookup_PPU!T:T,Lookup_PPU!S:S, "NOT FOUND") -> Item_2_MILK | E13: =G13/F13 -> 6.5 | F13: 8 | G13: 52 | H13: Digital Wallet | I13: In-store | J13: 45669 | K13: TRUE | L13: =IF(OR(F13="",G13=""),"skip",IF(ROUND(E13*F13,2)=ROUND(G13,2),"OK","MISMATCH")) -> OK | N13: 13 | O13: YES | P13: YES
A14: TXN_5874772 | B14: CUST_23 | C14: Food | D14: Item_2_FOOD | E14: 6.5 | F14: 7 | G14: 45.5 | H14: Cash | I14: Online | J14: 45178 | K14: TRUE | L14: =IF(OR(F14="",G14=""),"skip",IF(ROUND(E14*F14,2)=ROUND(G14,2),"OK","MISMATCH")) -> OK | N14: 14 | O14: NO | P14: NO
A15: TXN_4413070 | B15: CUST_14 | C15: Patisserie | D15: Item_24_PAT | E15: 39.5 | F15: 6 | G15: 237 | H15: Digital Wallet | I15: In-store | J15: 44701 | K15: FALSE | L15: =IF(OR(F15="",G15=""),"skip",IF(ROUND(E15*F15,2)=ROUND(G15,2),"OK","MISMATCH")) -> OK | N15: 15 | O15: NO | P15: NO
A16: TXN_2490363 | B16: CUST_09 | C16: Milk Products | D16: Item_16_MILK | E16: 27.5 | F16: 2 | G16: 55 | H16: Digital Wallet | I16: Online | J16: 44703 | L16: =IF(OR(F16="",G16=""),"skip",IF(ROUND(E16*F16,2)=ROUND(G16,2),"OK","MISMATCH")) -> OK | N16: 16 | O16: NO | P16: NO
A17: TXN_1809665 | B17: CUST_14 | C17: Beverages | D17: =_xlfn.XLOOKUP(E17,Lookup_PPU!B:B,Lookup_PPU!A:A, "NOT FOUND") -> Item_14_BEV | E17: 24.5 | H17: Credit Card | I17: In-store | J17: 44692 | L17: =IF(OR(F17="",G17=""),"skip",IF(ROUND(E17*F17,2)=ROUND(G17,2),"OK","MISMATCH")) -> skip | N17: 17 | O17: YES | P17: NO
A18: TXN_7563311 | B18: CUST_23 | C18: Patisserie | D18: Item_17_PAT | E18: 29 | F18: 8 | G18: 232 | H18: Cash | I18: Online | J18: 45612 | K18: TRUE | L18: =IF(OR(F18="",G18=""),"skip",IF(ROUND(E18*F18,2)=ROUND(G18,2),"OK","MISMATCH")) -> OK | N18: 18 | O18: NO | P18: NO
A19: TXN_9634894 | B19: CUST_15 | C19: Milk Products | D19: =_xlfn.XLOOKUP(E19,Lookup_PPU!T:T,Lookup_PPU!S:S, "NOT FOUND") -> Item_16_MILK | E19: =G19/F19 -> 27.5 | F19: 10 | G19: 275 | H19: Digital Wallet | I19: Online | J19: 44668 | L19: =IF(OR(F19="",G19=""),"skip",IF(ROUND(E19*F19,2)=ROUND(G19,2),"OK","MISMATCH")) -> OK | N19: 19 | O19: YES | P19: YES
A20: TXN_4396807 | B20: CUST_17 | C20: Electric household essentials | D20: Item_13_EHE | E20: 23 | F20: 1 | G20: 23 | H20: Digital Wallet | I20: In-store | J20: 44599 | K20: FALSE | L20: =IF(OR(F20="",G20=""),"skip",IF(ROUND(E20*F20,2)=ROUND(G20,2),"OK","MISMATCH")) -> OK | N20: 20 | O20: NO | P20: NO
A21: TXN_4206593 | B21: CUST_01 | C21: Furniture | D21: =_xlfn.XLOOKUP(E21,Lookup_PPU!Q:Q,Lookup_PPU!P:P, "NOT FOUND") -> Item_21_FUR | E21: 35 | H21: Digital Wallet | I21: Online | J21: 45670 | K21: FALSE | L21: =IF(OR(F21="",G21=""),"skip",IF(ROUND(E21*F21,2)=ROUND(G21,2),"OK","MISMATCH")) -> skip | N21: 21 | O21: YES | P21: NO
A22: TXN_9939063 | B22: CUST_14 | C22: Beverages | D22: Item_7_BEV | E22: 14 | F22: 9 | G22: 126 | H22: Digital Wallet | I22: In-store | J22: 45305 | L22: =IF(OR(F22="",G22=""),"skip",IF(ROUND(E22*F22,2)=ROUND(G22,2),"OK","MISMATCH")) -> OK | N22: 22 | O22: NO | P22: NO
A23: TXN_8685338 | B23: CUST_15 | C23: Milk Products | D23: =_xlfn.XLOOKUP(E23,Lookup_PPU!T:T,Lookup_PPU!S:S, "NOT FOUND") -> Item_21_MILK | E23: =G23/F23 -> 35 | F23: 3 | G23: 105 | H23: Credit Card | I23: In-store | J23: 45228 | L23: =IF(OR(F23="",G23=""),"skip",IF(ROUND(E23*F23,2)=ROUND(G23,2),"OK","MISMATCH")) -> OK | N23: 23 | O23: YES | P23: YES
A24: TXN_6547964 | B24: CUST_10 | C24: Electric household essentials | D24: Item_4_EHE | E24: 9.5 | F24: 7 | G24: 66.5 | H24: Cash | I24: In-store | J24: 44788 | L24: =IF(OR(F24="",G24=""),"skip",IF(ROUND(E24*F24,2)=ROUND(G24,2),"OK","MISMATCH")) -> OK | N24: 24 | O24: NO | P24: NO
A25: TXN_3314099 | B25: CUST_04 | C25: Food | D25: Item_10_FOOD | E25: 18.5 | F25: 1 | G25: 18.5 | H25: Cash | I25: Online | J25: 45199 | K25: FALSE | L25: =IF(OR(F25="",G25=""),"skip",IF(ROUND(E25*F25,2)=ROUND(G25,2),"OK","MISMATCH")) -> OK | N25: 25 | O25: NO | P25: NO
A26: TXN_9980736 | B26: CUST_13 | C26: Furniture | D26: Item_14_FUR | E26: 24.5 | F26: 2 | G26: 49 | H26: Cash | I26: Online | J26: 45167 | K26: FALSE | L26: =IF(OR(F26="",G26=""),"skip",IF(ROUND(E26*F26,2)=ROUND(G26,2),"OK","MISMATCH")) -> OK | N26: 26 | O26: NO | P26: NO
A27: TXN_3481599 | B27: CUST_05 | C27: Furniture | D27: =_xlfn.XLOOKUP(E27,Lookup_PPU!Q:Q,Lookup_PPU!P:P, "NOT FOUND") -> Item_24_FUR | E27: 39.5 | H27: Cash | I27: Online | J27: 44812 | K27: FALSE | L27: =IF(OR(F27="",G27=""),"skip",IF(ROUND(E27*F27,2)=ROUND(G27,2),"OK","MISMATCH")) -> skip | N27: 27 | O27: YES | P27: NO
A28: TXN_9057609 | B28: CUST_18 | C28: Butchers | D28: Item_20_BUT | E28: 33.5 | F28: 4 | G28: 134 | H28: Credit Card | I28: In-store | J28: 44636 | K28: TRUE | L28: =IF(OR(F28="",G28=""),"skip",IF(ROUND(E28*F28,2)=ROUND(G28,2),"OK","MISMATCH")) -> OK | N28: 28 | O28: NO | P28: NO
A29: TXN_1599706 | B29: CUST_14 | C29: Furniture | D29: Item_25_FUR | E29: 41 | F29: 10 | G29: 410 | H29: Credit Card | I29: In-store | J29: 45375 | K29: TRUE | L29: =IF(OR(F29="",G29=""),"skip",IF(ROUND(E29*F29,2)=ROUND(G29,2),"OK","MISMATCH")) -> OK | N29: 29 | O29: NO | P29: NO
A30: TXN_1598860 | B30: CUST_08 | C30: Food | D30: Item_14_FOOD | E30: 24.5 | F30: 10 | G30: 245 | H30: Cash | I30: In-store | J30: 44857 | K30: TRUE | L30: =IF(OR(F30="",G30=""),"skip",IF(ROUND(E30*F30,2)=ROUND(G30,2),"OK","MISMATCH")) -> OK | N30: 30 | O30: NO | P30: NO
A31: TXN_7138501 | B31: CUST_18 | C31: Patisserie | D31: Item_22_PAT | E31: 36.5 | F31: 5 | G31: 182.5 | H31: Credit Card | I31: In-store | J31: 44630 | K31: FALSE | L31: =IF(OR(F31="",G31=""),"skip",IF(ROUND(E31*F31,2)=ROUND(G31,2),"OK","MISMATCH")) -> OK | N31: 31 | O31: NO | P31: NO
A32: TXN_5444504 | B32: CUST_05 | C32: Food | D32: Item_11_FOOD | E32: 20 | F32: 10 | G32: 200 | H32: Digital Wallet | I32: Online | J32: 44677 | K32: FALSE | L32: =IF(OR(F32="",G32=""),"skip",IF(ROUND(E32*F32,2)=ROUND(G32,2),"OK","MISMATCH")) -> OK | N32: 32 | O32: NO | P32: NO
A33: TXN_4353295 | B33: CUST_22 | C33: Patisserie | D33: Item_6_PAT | E33: 12.5 | F33: 8 | G33: 100 | H33: Credit Card | I33: Online | J33: 44656 | K33: TRUE | L33: =IF(OR(F33="",G33=""),"skip",IF(ROUND(E33*F33,2)=ROUND(G33,2),"OK","MISMATCH")) -> OK | N33: 33 | O33: NO | P33: NO
A34: TXN_1543244 | B34: CUST_20 | C34: Food | D34: =_xlfn.XLOOKUP(E34,Lookup_PPU!N:N,Lookup_PPU!M:M, "NOT FOUND") -> Item_14_FOOD | E34: =G34/F34 -> 24.5 | F34: 8 | G34: 196 | H34: Credit Card | I34: Online | J34: 45590 | K34: TRUE | L34: =IF(OR(F34="",G34=""),"skip",IF(ROUND(E34*F34,2)=ROUND(G34,2),"OK","MISMATCH")) -> OK | N34: 34 | O34: YES | P34: YES
A35: TXN_1494700 | B35: CUST_12 | C35: Electric household essentials | D35: Item_21_EHE | E35: 35 | F35: 9 | G35: 315 | H35: Credit Card | I35: In-store | J35: 45358 | L35: =IF(OR(F35="",G35=""),"skip",IF(ROUND(E35*F35,2)=ROUND(G35,2),"OK","MISMATCH")) -> OK | N35: 35 | O35: NO | P35: NO
A36: TXN_1621497 | B36: CUST_06 | C36: Patisserie | D36: =_xlfn.XLOOKUP(E36,Lookup_PPU!W:W,Lookup_PPU!V:V,"NOT FOUND") -> Item_13_PAT | E36: 23 | H36: Cash | I36: In-store | J36: 44975 | L36: =IF(OR(F36="",G36=""),"skip",IF(ROUND(E36*F36,2)=ROUND(G36,2),"OK","MISMATCH")) -> skip | N36: 36 | O36: YES | P36: NO
A37: TXN_6398436 | B37: CUST_15 | C37: Beverages | D37: Item_25_BEV | E37: 41 | F37: 7 | G37: 287 | H37: Credit Card | I37: In-store | J37: 45446 | K37: TRUE | L37: =IF(OR(F37="",G37=""),"skip",IF(ROUND(E37*F37,2)=ROUND(G37,2),"OK","MISMATCH")) -> OK | N37: 37 | O37: NO | P37: NO
A38: TXN_9065245 | B38: CUST_02 | C38: Food | D38: Item_23_FOOD | E38: 38 | F38: 2 | G38: 76 | H38: Digital Wallet | I38: In-store | J38: 45361 | K38: FALSE | L38: =IF(OR(F38="",G38=""),"skip",IF(ROUND(E38*F38,2)=ROUND(G38,2),"OK","MISMATCH")) -> OK | N38: 38 | O38: NO | P38: NO
A39: TXN_6963438 | B39: CUST_11 | C39: Furniture | D39: Item_10_FUR | E39: 18.5 | F39: 5 | G39: 92.5 | H39: Credit Card | I39: Online | J39: 45405 | K39: TRUE | L39: =IF(OR(F39="",G39=""),"skip",IF(ROUND(E39*F39,2)=ROUND(G39,2),"OK","MISMATCH")) -> OK | N39: 39 | O39: NO | P39: NO
A40: TXN_8312797 | B40: CUST_14 | C40: Beverages | D40: Item_11_BEV | E40: 20 | F40: 5 | G40: 100 | H40: Digital Wallet | I40: Online | J40: 44715 | L40: =IF(OR(F40="",G40=""),"skip",IF(ROUND(E40*F40,2)=ROUND(G40,2),"OK","MISMATCH")) -> OK | N40: 40 | O40: NO | P40: NO
A41: TXN_5836005 | B41: CUST_19 | C41: Butchers | D41: Item_23_BUT | E41: 38 | F41: 5 | G41: 190 | H41: Credit Card | I41: In-store | J41: 45584 | K41: FALSE | L41: =IF(OR(F41="",G41=""),"skip",IF(ROUND(E41*F41,2)=ROUND(G41,2),"OK","MISMATCH")) -> OK | N41: 41 | O41: NO | P41: NO
A42: TXN_4223250 | B42: CUST_16 | C42: Beverages | D42: Item_22_BEV | E42: 36.5 | F42: 7 | G42: 255.5 | H42: Cash | I42: Online | J42: 45077 | K42: TRUE | L42: =IF(OR(F42="",G42=""),"skip",IF(ROUND(E42*F42,2)=ROUND(G42,2),"OK","MISMATCH")) -> OK | N42: 42 | O42: NO | P42: NO
A43: TXN_1019817 | B43: CUST_16 | C43: Electric household essentials | D43: Item_10_EHE | E43: 18.5 | F43: 5 | G43: 92.5 | H43: Cash | I43: Online | J43: 44774 | L43: =IF(OR(F43="",G43=""),"skip",IF(ROUND(E43*F43,2)=ROUND(G43,2),"OK","MISMATCH")) -> OK | N43: 43 | O43: NO | P43: NO
A44: TXN_1110407 | B44: CUST_25 | C44: Butchers | D44: Item_24_BUT | E44: 39.5 | F44: 7 | G44: 276.5 | H44: Digital Wallet | I44: In-store | J44: 44855 | L44: =IF(OR(F44="",G44=""),"skip",IF(ROUND(E44*F44,2)=ROUND(G44,2),"OK","MISMATCH")) -> OK | N44: 44 | O44: NO | P44: NO
A45: TXN_6276518 | B45: CUST_24 | C45: Beverages | D45: Item_8_BEV | E45: 15.5 | F45: 3 | G45: 46.5 | H45: Cash | I45: In-store | J45: 45390 | L45: =IF(OR(F45="",G45=""),"skip",IF(ROUND(E45*F45,2)=ROUND(G45,2),"OK","MISMATCH")) -> OK | N45: 45 | O45: NO | P45: NO
A46: TXN_4740738 | B46: CUST_25 | C46: Food | D46: Item_3_FOOD | E46: 8 | F46: 1 | G46: 8 | H46: Digital Wallet | I46: In-store | J46: 44670 | L46: =IF(OR(F46="",G46=""),"skip",IF(ROUND(E46*F46,2)=ROUND(G46,2),"OK","MISMATCH")) -> OK | N46: 46 | O46: NO | P46: NO
A47: TXN_9587232 | B47: CUST_20 | C47: Food | D47: Item_12_FOOD | E47: 21.5 | F47: 5 | G47: 107.5 | H47: Digital Wallet | I47: Online | J47: 44985 | K47: TRUE | L47: =IF(OR(F47="",G47=""),"skip",IF(ROUND(E47*F47,2)=ROUND(G47,2),"OK","MISMATCH")) -> OK | N47: 47 | O47: NO | P47: NO
A48: TXN_6404316 | B48: CUST_04 | C48: Computers and electric accessories | D48: Item_16_CEA | E48: 27.5 | F48: 6 | G48: 165 | H48: Credit Card | I48: Online | J48: 44657 | K48: FALSE | L48: =IF(OR(F48="",G48=""),"skip",IF(ROUND(E48*F48,2)=ROUND(G48,2),"OK","MISMATCH")) -> OK | N48: 48 | O48: NO | P48: NO
A49: TXN_9331642 | B49: CUST_12 | C49: Patisserie | D49: Item_11_PAT | E49: 20 | F49: 4 | G49: 80 | H49: Credit Card | I49: Online | J49: 44748 | K49: TRUE | L49: =IF(OR(F49="",G49=""),"skip",IF(ROUND(E49*F49,2)=ROUND(G49,2),"OK","MISMATCH")) -> OK | N49: 49 | O49: NO | P49: NO
A50: TXN_9729422 | B50: CUST_13 | C50: Butchers | D50: Item_16_BUT | E50: 27.5 | F50: 6 | G50: 165 | H50: Credit Card | I50: Online | J50: 45657 | K50: TRUE | L50: =IF(OR(F50="",G50=""),"skip",IF(ROUND(E50*F50,2)=ROUND(G50,2),"OK","MISMATCH")) -> OK | N50: 50 | O50: NO | P50: NO
A51: TXN_8425168 | B51: CUST_25 | C51: Milk Products | D51: Item_16_MILK | E51: 27.5 | F51: 7 | G51: 192.5 | H51: Cash | I51: In-store | J51: 44632 | L51: =IF(OR(F51="",G51=""),"skip",IF(ROUND(E51*F51,2)=ROUND(G51,2),"OK","MISMATCH")) -> OK | N51: 51 | O51: NO | P51: NO
A52: TXN_5379241 | B52: CUST_05 | C52: Butchers | D52: Item_20_BUT | E52: 33.5 | F52: 10 | G52: 335 | H52: Credit Card | I52: In-store | J52: 45028 | K52: FALSE | L52: =IF(OR(F52="",G52=""),"skip",IF(ROUND(E52*F52,2)=ROUND(G52,2),"OK","MISMATCH")) -> OK | N52: 52 | O52: NO | P52: NO
A53: TXN_8413369 | B53: CUST_23 | C53: Computers and electric accessories | D53: Item_5_CEA | E53: 11 | F53: 6 | G53: 66 | H53: Credit Card | I53: Online | J53: 45360 | K53: TRUE | L53: =IF(OR(F53="",G53=""),"skip",IF(ROUND(E53*F53,2)=ROUND(G53,2),"OK","MISMATCH")) -> OK | N53: 53 | O53: NO | P53: NO
A54: TXN_4836321 | B54: CUST_21 | C54: Food | D54: Item_12_FOOD | E54: 21.5 | F54: 10 | G54: 215 | H54: Digital Wallet | I54: In-store | J54: 44940 | K54: FALSE | L54: =IF(OR(F54="",G54=""),"skip",IF(ROUND(E54*F54,2)=ROUND(G54,2),"OK","MISMATCH")) -> OK | N54: 54 | O54: NO | P54: NO
A55: TXN_9451794 | B55: CUST_24 | C55: Milk Products | D55: Item_19_MILK | E55: 32 | F55: 3 | G55: 96 | H55: Credit Card | I55: Online | J55: 45319 | L55: =IF(OR(F55="",G55=""),"skip",IF(ROUND(E55*F55,2)=ROUND(G55,2),"OK","MISMATCH")) -> OK | N55: 55 | O55: NO | P55: NO
A56: TXN_8218431 | B56: CUST_01 | C56: Furniture | D56: Item_23_FUR | E56: 38 | F56: 5 | G56: 190 | H56: Digital Wallet | I56: Online | J56: 45045 | K56: FALSE | L56: =IF(OR(F56="",G56=""),"skip",IF(ROUND(E56*F56,2)=ROUND(G56,2),"OK","MISMATCH")) -> OK | N56: 56 | O56: NO | P56: NO
A57: TXN_2383377 | B57: CUST_15 | C57: Furniture | D57: Item_7_FUR | E57: 14 | F57: 3 | G57: 42 | H57: Digital Wallet | I57: In-store | J57: 45018 | L57: =IF(OR(F57="",G57=""),"skip",IF(ROUND(E57*F57,2)=ROUND(G57,2),"OK","MISMATCH")) -> OK | N57: 57 | O57: NO | P57: NO
A58: TXN_7909783 | B58: CUST_12 | C58: Computers and electric accessories | D58: Item_5_CEA | E58: 11 | F58: 1 | G58: 11 | H58: Credit Card | I58: Online | J58: 45277 | K58: TRUE | L58: =IF(OR(F58="",G58=""),"skip",IF(ROUND(E58*F58,2)=ROUND(G58,2),"OK","MISMATCH")) -> OK | N58: 58 | O58: NO | P58: NO
A59: TXN_5046007 | B59: CUST_07 | C59: Computers and electric accessories | D59: Item_15_CEA | E59: 26 | F59: 9 | G59: 234 | H59: Cash | I59: Online | J59: 45495 | K59: TRUE | L59: =IF(OR(F59="",G59=""),"skip",IF(ROUND(E59*F59,2)=ROUND(G59,2),"OK","MISMATCH")) -> OK | N59: 59 | O59: NO | P59: NO
A60: TXN_6966182 | B60: CUST_02 | C60: Furniture | D60: Item_16_FUR | E60: 27.5 | F60: 9 | G60: 247.5 | H60: Cash | I60: Online | J60: 45541 | L60: =IF(OR(F60="",G60=""),"skip",IF(ROUND(E60*F60,2)=ROUND(G60,2),"OK","MISMATCH")) -> OK | N60: 60 | O60: NO | P60: NO
A61: TXN_3424571 | B61: CUST_09 | C61: Milk Products | D61: Item_6_MILK | E61: 12.5 | F61: 7 | G61: 87.5 | H61: Credit Card | I61: Online | J61: 44939 | K61: FALSE | L61: =IF(OR(F61="",G61=""),"skip",IF(ROUND(E61*F61,2)=ROUND(G61,2),"OK","MISMATCH")) -> OK | N61: 61 | O61: NO | P61: NO
A62: TXN_6820452 | B62: CUST_10 | C62: Computers and electric accessories | D62: Item_24_CEA | E62: 39.5 | F62: 8 | G62: 316 | H62: Credit Card | I62: In-store | J62: 45034 | K62: FALSE | L62: =IF(OR(F62="",G62=""),"skip",IF(ROUND(E62*F62,2)=ROUND(G62,2),"OK","MISMATCH")) -> OK | N62: 62 | O62: NO | P62: NO
A63: TXN_1998771 | B63: CUST_25 | C63: Milk Products | D63: Item_16_MILK | E63: 27.5 | F63: 3 | G63: 82.5 | H63: Digital Wallet | I63: Online | J63: 45603 | K63: TRUE | L63: =IF(OR(F63="",G63=""),"skip",IF(ROUND(E63*F63,2)=ROUND(G63,2),"OK","MISMATCH")) -> OK | N63: 63 | O63: NO | P63: NO
A64: TXN_1132097 | B64: CUST_24 | C64: Patisserie | D64: Item_11_PAT | E64: 20 | F64: 9 | G64: 180 | H64: Credit Card | I64: In-store | J64: 45064 | K64: TRUE | L64: =IF(OR(F64="",G64=""),"skip",IF(ROUND(E64*F64,2)=ROUND(G64,2),"OK","MISMATCH")) -> OK | N64: 64 | O64: NO | P64: NO
A65: TXN_5418871 | B65: CUST_04 | C65: Computers and electric accessories | D65: Item_22_CEA | E65: 36.5 | F65: 7 | G65: 255.5 | H65: Cash | I65: In-store | J65: 44636 | K65: FALSE | L65: =IF(OR(F65="",G65=""),"skip",IF(ROUND(E65*F65,2)=ROUND(G65,2),"OK","MISMATCH")) -> OK | N65: 65 | O65: NO | P65: NO
A66: TXN_6952276 | B66: CUST_01 | C66: Food | D66: Item_22_FOOD | E66: 36.5 | F66: 10 | G66: 365 | H66: Credit Card | I66: Online | J66: 45506 | K66: TRUE | L66: =IF(OR(F66="",G66=""),"skip",IF(ROUND(E66*F66,2)=ROUND(G66,2),"OK","MISMATCH")) -> OK | N66: 66 | O66: NO | P66: NO
A67: TXN_6340470 | B67: CUST_17 | C67: Butchers | D67: Item_2_BUT | E67: 6.5 | F67: 6 | G67: 39 | H67: Credit Card | I67: In-store | J67: 44846 | L67: =IF(OR(F67="",G67=""),"skip",IF(ROUND(E67*F67,2)=ROUND(G67,2),"OK","MISMATCH")) -> OK | N67: 67 | O67: NO | P67: NO
A68: TXN_5885894 | B68: CUST_01 | C68: Patisserie | D68: Item_14_PAT | E68: 24.5 | F68: 10 | G68: 245 | H68: Credit Card | I68: In-store | J68: 44601 | K68: FALSE | L68: =IF(OR(F68="",G68=""),"skip",IF(ROUND(E68*F68,2)=ROUND(G68,2),"OK","MISMATCH")) -> OK | N68: 68 | O68: NO | P68: NO
A69: TXN_3671271 | B69: CUST_18 | C69: Patisserie | D69: Item_12_PAT | E69: 21.5 | F69: 8 | G69: 172 | H69: Cash | I69: In-store | J69: 45257 | K69: FALSE | L69: =IF(OR(F69="",G69=""),"skip",IF(ROUND(E69*F69,2)=ROUND(G69,2),"OK","MISMATCH")) -> OK | N69: 69 | O69: NO | P69: NO
A70: TXN_2719047 | B70: CUST_03 | C70: Butchers | D70: Item_20_BUT | E70: 33.5 | F70: 4 | G70: 134 | H70: Credit Card | I70: Online | J70: 45251 | L70: =IF(OR(F70="",G70=""),"skip",IF(ROUND(E70*F70,2)=ROUND(G70,2),"OK","MISMATCH")) -> OK | N70: 70 | O70: NO | P70: NO
A71: TXN_9908330 | B71: CUST_19 | C71: Food | D71: Item_18_FOOD | E71: 30.5 | F71: 4 | G71: 122 | H71: Credit Card | I71: Online | J71: 44833 | K71: TRUE | L71: =IF(OR(F71="",G71=""),"skip",IF(ROUND(E71*F71,2)=ROUND(G71,2),"OK","MISMATCH")) -> OK | N71: 71 | O71: NO | P71: NO
A72: TXN_2016332 | B72: CUST_17 | C72: Patisserie | D72: Item_1_PAT | E72: 5 | F72: 6 | G72: 30 | H72: Digital Wallet | I72: Online | J72: 44912 | K72: TRUE | L72: =IF(OR(F72="",G72=""),"skip",IF(ROUND(E72*F72,2)=ROUND(G72,2),"OK","MISMATCH")) -> OK | N72: 72 | O72: NO | P72: NO
A73: TXN_7363165 | B73: CUST_25 | C73: Beverages | D73: Item_4_BEV | E73: 9.5 | F73: 7 | G73: 66.5 | H73: Digital Wallet | I73: In-store | J73: 45010 | L73: =IF(OR(F73="",G73=""),"skip",IF(ROUND(E73*F73,2)=ROUND(G73,2),"OK","MISMATCH")) -> OK | N73: 73 | O73: NO | P73: NO
A74: TXN_1260450 | B74: CUST_25 | C74: Furniture | D74: Item_22_FUR | E74: 36.5 | F74: 10 | G74: 365 | H74: Digital Wallet | I74: In-store | J74: 45284 | K74: TRUE | L74: =IF(OR(F74="",G74=""),"skip",IF(ROUND(E74*F74,2)=ROUND(G74,2),"OK","MISMATCH")) -> OK | N74: 74 | O74: NO | P74: NO
A75: TXN_6315447 | B75: CUST_21 | C75: Patisserie | D75: Item_7_PAT | E75: 14 | F75: 9 | G75: 126 | H75: Digital Wallet | I75: In-store | J75: 45669 | K75: FALSE | L75: =IF(OR(F75="",G75=""),"skip",IF(ROUND(E75*F75,2)=ROUND(G75,2),"OK","MISMATCH")) -> OK | N75: 75 | O75: NO | P75: NO
A76: TXN_5973228 | B76: CUST_12 | C76: Beverages | D76: Item_7_BEV | E76: 14 | F76: 6 | G76: 84 | H76: Digital Wallet | I76: Online | J76: 45285 | K76: TRUE | L76: =IF(OR(F76="",G76=""),"skip",IF(ROUND(E76*F76,2)=ROUND(G76,2),"OK","MISMATCH")) -> OK | N76: 76 | O76: NO | P76: NO
A77: TXN_2780662 | B77: CUST_02 | C77: Milk Products | D77: Item_19_MILK | E77: 32 | F77: 10 | G77: 320 | H77: Digital Wallet | I77: In-store | J77: 44945 | L77: =IF(OR(F77="",G77=""),"skip",IF(ROUND(E77*F77,2)=ROUND(G77,2),"OK","MISMATCH")) -> OK | N77: 77 | O77: NO | P77: NO
A78: TXN_1142481 | B78: CUST_02 | C78: Beverages | D78: Item_22_BEV | E78: 36.5 | F78: 6 | G78: 219 | H78: Cash | I78: In-store | J78: 44964 | K78: TRUE | L78: =IF(OR(F78="",G78=""),"skip",IF(ROUND(E78*F78,2)=ROUND(G78,2),"OK","MISMATCH")) -> OK | N78: 78 | O78: NO | P78: NO
A79: TXN_3933685 | B79: CUST_09 | C79: Computers and electric accessories | D79: Item_20_CEA | E79: 33.5 | F79: 10 | G79: 335 | H79: Credit Card | I79: Online | J79: 44666 | L79: =IF(OR(F79="",G79=""),"skip",IF(ROUND(E79*F79,2)=ROUND(G79,2),"OK","MISMATCH")) -> OK | N79: 79 | O79: NO | P79: NO
A80: TXN_8955685 | B80: CUST_24 | C80: Food | D80: Item_20_FOOD | E80: 33.5 | F80: 2 | G80: 67 | H80: Digital Wallet | I80: Online | J80: 45040 | L80: =IF(OR(F80="",G80=""),"skip",IF(ROUND(E80*F80,2)=ROUND(G80,2),"OK","MISMATCH")) -> OK | N80: 80 | O80: NO | P80: NO
A81: TXN_1061030 | B81: CUST_20 | C81: Computers and electric accessories | D81: Item_22_CEA | E81: 36.5 | F81: 4 | G81: 146 | H81: Digital Wallet | I81: Online | J81: 45487 | K81: TRUE | L81: =IF(OR(F81="",G81=""),"skip",IF(ROUND(E81*F81,2)=ROUND(G81,2),"OK","MISMATCH")) -> OK | N81: 81 | O81: NO | P81: NO
A82: TXN_7821493 | B82: CUST_07 | C82: Patisserie | D82: Item_17_PAT | E82: 29 | F82: 10 | G82: 290 | H82: Credit Card | I82: In-store | J82: 45643 | L82: =IF(OR(F82="",G82=""),"skip",IF(ROUND(E82*F82,2)=ROUND(G82,2),"OK","MISMATCH")) -> OK | N82: 82 | O82: NO | P82: NO
A83: TXN_8114453 | B83: CUST_10 | C83: Electric household essentials | D83: Item_21_EHE | E83: 35 | F83: 2 | G83: 70 | H83: Digital Wallet | I83: In-store | J83: 45055 | K83: FALSE | L83: =IF(OR(F83="",G83=""),"skip",IF(ROUND(E83*F83,2)=ROUND(G83,2),"OK","MISMATCH")) -> OK | N83: 83 | O83: NO | P83: NO
A84: TXN_8024803 | B84: CUST_09 | C84: Furniture | D84: Item_11_FUR | E84: 20 | F84: 8 | G84: 160 | H84: Digital Wallet | I84: In-store | J84: 45526 | K84: FALSE | L84: =IF(OR(F84="",G84=""),"skip",IF(ROUND(E84*F84,2)=ROUND(G84,2),"OK","MISMATCH")) -> OK | N84: 84 | O84: NO | P84: NO
A85: TXN_4532214 | B85: CUST_25 | C85: Patisserie | D85: =_xlfn.XLOOKUP(E85,Lookup_PPU!W:W,Lookup_PPU!V:V,"NOT FOUND") -> Item_8_PAT | E85: 15.5 | H85: Credit Card | I85: In-store | J85: 45376 | K85: FALSE | L85: =IF(OR(F85="",G85=""),"skip",IF(ROUND(E85*F85,2)=ROUND(G85,2),"OK","MISMATCH")) -> skip | N85: 85 | O85: YES | P85: NO
A86: TXN_5062634 | B86: CUST_04 | C86: Patisserie | D86: Item_25_PAT | E86: 41 | F86: 2 | G86: 82 | H86: Credit Card | I86: Online | J86: 45113 | K86: TRUE | L86: =IF(OR(F86="",G86=""),"skip",IF(ROUND(E86*F86,2)=ROUND(G86,2),"OK","MISMATCH")) -> OK | N86: 86 | O86: NO | P86: NO
A87: TXN_8244728 | B87: CUST_08 | C87: Food | D87: Item_7_FOOD | E87: 14 | F87: 1 | G87: 14 | H87: Credit Card | I87: In-store | J87: 45409 | L87: =IF(OR(F87="",G87=""),"skip",IF(ROUND(E87*F87,2)=ROUND(G87,2),"OK","MISMATCH")) -> OK | N87: 87 | O87: NO | P87: NO
A88: TXN_3858145 | B88: CUST_17 | C88: Furniture | D88: Item_21_FUR | E88: 35 | F88: 3 | G88: 105 | H88: Digital Wallet | I88: Online | J88: 45017 | L88: =IF(OR(F88="",G88=""),"skip",IF(ROUND(E88*F88,2)=ROUND(G88,2),"OK","MISMATCH")) -> OK | N88: 88 | O88: NO | P88: NO
A89: TXN_2646301 | B89: CUST_18 | C89: Furniture | D89: Item_24_FUR | E89: 39.5 | F89: 9 | G89: 355.5 | H89: Credit Card | I89: In-store | J89: 44902 | K89: FALSE | L89: =IF(OR(F89="",G89=""),"skip",IF(ROUND(E89*F89,2)=ROUND(G89,2),"OK","MISMATCH")) -> OK | N89: 89 | O89: NO | P89: NO
A90: TXN_2414530 | B90: CUST_24 | C90: Milk Products | D90: Item_8_MILK | E90: 15.5 | F90: 8 | G90: 124 | H90: Cash | I90: Online | J90: 45463 | L90: =IF(OR(F90="",G90=""),"skip",IF(ROUND(E90*F90,2)=ROUND(G90,2),"OK","MISMATCH")) -> OK | N90: 90 | O90: NO | P90: NO
A91: TXN_8322008 | B91: CUST_22 | C91: Food | D91: Item_4_FOOD | E91: 9.5 | F91: 3 | G91: 28.5 | H91: Cash | I91: In-store | J91: 45524 | K91: FALSE | L91: =IF(OR(F91="",G91=""),"skip",IF(ROUND(E91*F91,2)=ROUND(G91,2),"OK","MISMATCH")) -> OK | N91: 91 | O91: NO | P91: NO
A92: TXN_3035546 | B92: CUST_19 | C92: Beverages | D92: Item_14_BEV | E92: 24.5 | F92: 2 | G92: 49 | H92: Credit Card | I92: In-store | J92: 45119 | K92: TRUE | L92: =IF(OR(F92="",G92=""),"skip",IF(ROUND(E92*F92,2)=ROUND(G92,2),"OK","MISMATCH")) -> OK | N92: 92 | O92: NO | P92: NO
A93: TXN_7296720 | B93: CUST_18 | C93: Patisserie | D93: Item_4_PAT | E93: 9.5 | F93: 5 | G93: 47.5 | H93: Cash | I93: Online | J93: 45547 | L93: =IF(OR(F93="",G93=""),"skip",IF(ROUND(E93*F93,2)=ROUND(G93,2),"OK","MISMATCH")) -> OK | N93: 93 | O93: NO | P93: NO
A94: TXN_8414071 | B94: CUST_20 | C94: Patisserie | D94: Item_12_PAT | E94: 21.5 | F94: 9 | G94: 193.5 | H94: Cash | I94: In-store | J94: 45048 | K94: TRUE | L94: =IF(OR(F94="",G94=""),"skip",IF(ROUND(E94*F94,2)=ROUND(G94,2),"OK","MISMATCH")) -> OK | N94: 94 | O94: NO | P94: NO
A95: TXN_5705131 | B95: CUST_19 | C95: Milk Products | D95: Item_4_MILK | E95: 9.5 | F95: 4 | G95: 38 | H95: Digital Wallet | I95: Online | J95: 45378 | K95: TRUE | L95: =IF(OR(F95="",G95=""),"skip",IF(ROUND(E95*F95,2)=ROUND(G95,2),"OK","MISMATCH")) -> OK | N95: 95 | O95: NO | P95: NO
A96: TXN_5938028 | B96: CUST_18 | C96: Computers and electric accessories | D96: Item_7_CEA | E96: 14 | F96: 1 | G96: 14 | H96: Digital Wallet | I96: Online | J96: 44977 | K96: TRUE | L96: =IF(OR(F96="",G96=""),"skip",IF(ROUND(E96*F96,2)=ROUND(G96,2),"OK","MISMATCH")) -> OK | N96: 96 | O96: NO | P96: NO
A97: TXN_1958345 | B97: CUST_08 | C97: Electric household essentials | D97: Item_4_EHE | E97: 9.5 | F97: 8 | G97: 76 | H97: Cash | I97: In-store | J97: 45471 | L97: =IF(OR(F97="",G97=""),"skip",IF(ROUND(E97*F97,2)=ROUND(G97,2),"OK","MISMATCH")) -> OK | N97: 97 | O97: NO | P97: NO
A98: TXN_1528585 | B98: CUST_15 | C98: Electric household essentials | D98: Item_6_EHE | E98: 12.5 | F98: 1 | G98: 12.5 | H98: Credit Card | I98: In-store | J98: 45552 | L98: =IF(OR(F98="",G98=""),"skip",IF(ROUND(E98*F98,2)=ROUND(G98,2),"OK","MISMATCH")) -> OK | N98: 98 | O98: NO | P98: NO
A99: TXN_9619859 | B99: CUST_01 | C99: Butchers | D99: Item_21_BUT | E99: 35 | F99: 4 | G99: 140 | H99: Cash | I99: In-store | J99: 45387 | K99: FALSE | L99: =IF(OR(F99="",G99=""),"skip",IF(ROUND(E99*F99,2)=ROUND(G99,2),"OK","MISMATCH")) -> OK | N99: 99 | O99: NO | P99: NO
A100: TXN_6158929 | B100: CUST_21 | C100: Food | D100: Item_11_FOOD | E100: 20 | F100: 6 | G100: 120 | H100: Cash | I100: Online | J100: 44590 | K100: TRUE | L100: =IF(OR(F100="",G100=""),"skip",IF(ROUND(E100*F100,2)=ROUND(G100,2),"OK","MISMATCH")) -> OK | N100: 100 | O100: NO | P100: NO
...

Sheet Issue_log
A1: Issue | B1: Rows affected | C1: How found | D1: Action taken | E1: Result / check
A2: Missing Price Per Unit | B2: 609 | C2: COUNTBLANK on raw data; all 609 also had a blank Item, with Quantity and Total Spent present | D2: Calculated Price Per Unit = Total Spent ÷ Quantity, rounded to 2 decimals. Marked Yes in the Price Imputed column | E2: 0 blanks remaining; Price × Quantity = Total Spent on all complete rows
A3: Missing Item | B3: 1,213 | C3: COUNTBLANK on raw data; 609 rows also had a blank Price Per Unit, 604 rows also had blank Quantity and Total Spent | D3: Recovered Item using a Category + Price Per Unit lookup (each item has one fixed price within its category). Marked Yes in the Item Imputed column | E3: 0 blanks remaining; Item codes match their category
A4: Missing Quantity | B4: 604 | C4: COUNTBLANK on raw data; always blank together with Total Spent | D4: Left blank. Neither Quantity nor Total Spent can be calculated from the other, so no reliable value exists. No averages or guesses used | E4: 604 blanks intentionally retained
A5: Missing Total Spent | B5: 604 | C5: COUNTBLANK on raw data; same 604 rows as missing Quantity | D5: Left blank for the same reason as Quantity | E5: 604 blanks intentionally retained
A6: Missing Discount Applied | B6: 4,199 | C6: COUNTBLANK on raw data | D6: Left blank. Total Spent equals Price × Quantity whether or not a discount is marked, so the value cannot be inferred | E6: 4,199 blanks intentionally retained
A7: Total Spent consistency | B7: 11,971 checked (604 skipped) | C7: Helper column: ROUND(Price × Quantity, 2) compared with Total Spent | D7: No changes needed. The 604 rows with blank Quantity and Total Spent were skipped | E7: 0 mismatches
A8: Duplicate records | B8: 12,575 checked | C8: Duplicate check on Transaction ID | D8: None found, no rows removed | E8: 0 duplicates
A9: Invalid or inconsistent values | B9: 12,575 checked | C9: Pivot table of distinct values; min/max checks | D9: Categories (8), Payment Method (3), Location (2) and Discount Applied (TRUE, FALSE or blank) all valid. Price Per Unit range 5 to 41, Quantity range 1 to 10 | E9: No invalid values found
A10: Date validity | B10: 12,575 checked | C10: Min/max date check | D10: Dates run from 01-01-2022 to 18-01-2025, all valid | E10: No issues found
A11: Item and category consistency | B11: 12,575 checked | C11: Item code suffix compared with its Category | D11: Every Item belongs to its own Category | E11: 0 mismatches
A12: Row count | B12: 12,575 data rows | C12: Row count before and after cleaning | D12: No rows added or deleted | E12: 12,575 before, 12,575 after

Sheet Profiling
A1: Data profiling (raw data, before cleaning)
A3: Category | C3: Payment Method | E3: Location | G3: Discount Applied | J3: Row Labels | K3: Count of Item_Imputed
A4: Beverages | C4: Cash | E4: In-store | G4: FALSE | J4: NO | K4: 11362
A5: Butchers | C5: Credit Card | E5: Online | G5: TRUE | J5: NO | K5: 11362
A6: Computers and electric accessories | C6: Digital Wallet | E6: Grand Total | G6: (blank) | J6: YES | K6: 1213
A7: Electric household essentials | C7: Grand Total | G7: Grand Total | J7: NO | K7: 604
A8: Food | J8: YES | K8: 609
A9: Furniture | J9: (blank)
A10: Milk Products | J10: (blank)
A11: Patisserie | J11: Grand Total | K11: 12575
A12: Grand Total
A15: MIN ppu | B15: 5
A16: MAX ppu | B16: 41
A17: MIN quantity | B17: 1
A18: MAX quantity | B18: 10
A19: Earliest Date | B19: =MIN(Cleaned_Data!J:J) -> 44562
A20: Latest Date | B20: =MAX(Cleaned_Data!J:J) -> 45675
A22: Row Count | B22: 12575
A23: Column Count | B23: 11
A25: Blank counts per column (after cleaning)
A26: Transaction ID | B26: Customer ID | C26: Category | D26: Item | E26: Price Per Unit | F26: Quantity | G26: Total Spent | H26: Payment Method | I26: Location | J26: Transaction Date | K26: Discount Applied
A27: =COUNTBLANK(Cleaned_Data!A1:A12576) -> 0 | B27: =COUNTBLANK(Cleaned_Data!B1:B12576) -> 0 | C27: =COUNTBLANK(Cleaned_Data!C1:C12576) -> 0 | D27: =COUNTBLANK(Cleaned_Data!D1:D12576) -> 0 | E27: =COUNTBLANK(Cleaned_Data!E1:E12576) -> 0 | F27: =COUNTBLANK(Cleaned_Data!F1:F12576) -> 604 | G27: =COUNTBLANK(Cleaned_Data!G1:G12576) -> 604 | H27: =COUNTBLANK(Cleaned_Data!H1:H12576) -> 0 | ... K27: =COUNTBLANK(Cleaned_Data!K1:K12576) -> 4199
A28: NO duplicate Transaction ID

Sheet Lookup_PPU
A1: Beverages | D1: Butchers | G1: Computers and electric accessories | J1: Electric household essentials | M1: Food | P1: Furniture | S1: Milk Products | V1: Patisserie
A2: Item_1_BEV | B2: 5 | D2: Item_1_BUT | E2: 5 | G2: Item_1_CEA | H2: 5 | J2: Item_1_EHE | K2: 5 | M2: Item_1_FOOD | N2: 5 | P2: Item_1_FUR | Q2: 5 | S2: Item_1_MILK | T2: 5 | V2: Item_1_PAT | W2: 5
A3: Item_2_BEV | B3: 6.5 | D3: Item_2_BUT | E3: 6.5 | G3: Item_2_CEA | H3: 6.5 | J3: Item_2_EHE | K3: 6.5 | M3: Item_2_FOOD | N3: 6.5 | P3: Item_2_FUR | Q3: 6.5 | S3: Item_2_MILK | T3: 6.5 | V3: Item_2_PAT | W3: 6.5
A4: Item_3_BEV | B4: 8 | D4: Item_3_BUT | E4: 8 | G4: Item_3_CEA | H4: 8 | J4: Item_3_EHE | K4: 8 | M4: Item_3_FOOD | N4: 8 | P4: Item_3_FUR | Q4: 8 | S4: Item_3_MILK | T4: 8 | V4: Item_3_PAT | W4: 8
A5: Item_4_BEV | B5: 9.5 | D5: Item_4_BUT | E5: 9.5 | G5: Item_4_CEA | H5: 9.5 | J5: Item_4_EHE | K5: 9.5 | M5: Item_4_FOOD | N5: 9.5 | P5: Item_4_FUR | Q5: 9.5 | S5: Item_4_MILK | T5: 9.5 | V5: Item_4_PAT | W5: 9.5
A6: Item_5_BEV | B6: 11 | D6: Item_5_BUT | E6: 11 | G6: Item_5_CEA | H6: 11 | J6: Item_5_EHE | K6: 11 | M6: Item_5_FOOD | N6: 11 | P6: Item_5_FUR | Q6: 11 | S6: Item_5_MILK | T6: 11 | V6: Item_5_PAT | W6: 11
A7: Item_6_BEV | B7: 12.5 | D7: Item_6_BUT | E7: 12.5 | G7: Item_6_CEA | H7: 12.5 | J7: Item_6_EHE | K7: 12.5 | M7: Item_6_FOOD | N7: 12.5 | P7: Item_6_FUR | Q7: 12.5 | S7: Item_6_MILK | T7: 12.5 | V7: Item_6_PAT | W7: 12.5
A8: Item_7_BEV | B8: 14 | D8: Item_7_BUT | E8: 14 | G8: Item_7_CEA | H8: 14 | J8: Item_7_EHE | K8: 14 | M8: Item_7_FOOD | N8: 14 | P8: Item_7_FUR | Q8: 14 | S8: Item_7_MILK | T8: 14 | V8: Item_7_PAT | W8: 14
A9: Item_8_BEV | B9: 15.5 | D9: Item_8_BUT | E9: 15.5 | G9: Item_8_CEA | H9: 15.5 | J9: Item_8_EHE | K9: 15.5 | M9: Item_8_FOOD | N9: 15.5 | P9: Item_8_FUR | Q9: 15.5 | S9: Item_8_MILK | T9: 15.5 | V9: Item_8_PAT | W9: 15.5
A10: Item_9_BEV | B10: 17 | D10: Item_9_BUT | E10: 17 | G10: Item_9_CEA | H10: 17 | J10: Item_9_EHE | K10: 17 | M10: Item_9_FOOD | N10: 17 | P10: Item_9_FUR | Q10: 17 | S10: Item_9_MILK | T10: 17 | V10: Item_9_PAT | W10: 17
A11: Item_10_BEV | B11: 18.5 | D11: Item_10_BUT | E11: 18.5 | G11: Item_10_CEA | H11: 18.5 | J11: Item_10_EHE | K11: 18.5 | M11: Item_10_FOOD | N11: 18.5 | P11: Item_10_FUR | Q11: 18.5 | S11: Item_10_MILK | T11: 18.5 | V11: Item_10_PAT | W11: 18.5
A12: Item_11_BEV | B12: 20 | D12: Item_11_BUT | E12: 20 | G12: Item_11_CEA | H12: 20 | J12: Item_11_EHE | K12: 20 | M12: Item_11_FOOD | N12: 20 | P12: Item_11_FUR | Q12: 20 | S12: Item_11_MILK | T12: 20 | V12: Item_11_PAT | W12: 20
A13: Item_12_BEV | B13: 21.5 | D13: Item_12_BUT | E13: 21.5 | G13: Item_12_CEA | H13: 21.5 | J13: Item_12_EHE | K13: 21.5 | M13: Item_12_FOOD | N13: 21.5 | P13: Item_12_FUR | Q13: 21.5 | S13: Item_12_MILK | T13: 21.5 | V13: Item_12_PAT | W13: 21.5
... A26: Item_25_BEV | B26: 41 | D26: Item_25_BUT | E26: 41 | G26: Item_25_CEA | H26: 41 | J26: Item_25_EHE | K26: 41 | M26: Item_25_FOOD | N26: 41 | P26: Item_25_FUR | Q26: 41 | S26: Item_25_MILK | T26: 41 | V26: Item_25_PAT | W26: 41
